{
  "chunkId": "nghi-dinh-168-2025-dieu93-chunk1",
  "category": "HO_KINH_DOANH",
  "title": "Nghị định 168/2025/NĐ-CP về đăng ký doanh nghiệp",
  "article": "Điều 93",
  "url": "https://xaydungchinhsach.chinhphu.vn/toan-van-nghi-dinh-168-2025-nd-cp-ve-dang-ky-doanh-nghiep-119250702175708554.htm",
  "sourceVersion": "168/2025/NĐ-CP (hiệu lực 01/07/2025)",
  "text": "Điều 93. ủy quyền thực hiện thủ tục đăng ký hộ kinh doanh\nChủ hộ kinh doanh có thể ủy quyền cho tổ chức, cá nhân khác thực hiện thủ tục đăng ký hộ kinh doanh theo quy định sau đây:\n1. Trường hợp ủy quyền cho cá nhân thực hiện thủ tục đăng ký hộ kinh doanh, kèm theo hồ sơ đăng ký hộ kinh doanh phải có văn bản ủy quyền cho cá nhân thực hiện thủ tục liên quan đến đăng ký hộ kinh doanh. Văn bản ủy quyền này không bắt buộc phải công chứng, chứng thực.\n2. Trường hợp ủy quyền cho tổ chức thực hiện thủ tục đăng ký hộ kinh doanh, kèm theo hồ sơ đăng ký hộ kinh doanh phải có bản sao hợp đồng cung cấp dịch vụ với tổ chức làm dịch vụ thực hiện thủ tục liên quan đến đăng ký hộ kinh doanh, giấy giới thiệu của tổ chức đó cho cá nhân trực tiếp thực hiện thủ tục liên quan đến đăng ký hộ kinh doanh.\n3. Trường hợp ủy quyền cho đơn vị cung cấp dịch vụ bưu chính công ích thực hiện thủ tục đăng ký hộ kinh doanh thì khi thực hiện thủ tục đăng ký hộ kinh doanh, nhân viên bưu chính phải nộp bản sao phiếu gửi hồ sơ theo mẫu do doanh nghiệp cung ứng dịch vụ bưu chính công ích phát hành có chữ ký xác nhận của nhân viên bưu chính và chủ hộ kinh doanh.\n4. Trường hợp ủy quyền cho đơn vị cung cấp dịch vụ bưu chính không phải là bưu chính công ích thực hiện thủ tục đăng ký hộ kinh doanh thì việc ủy quyền thực hiện theo quy định tại khoản 2 Điều này.\n5. Người ủy quyền và người được ủy quyền thực hiện thủ tục đăng ký hộ kinh doanh chịu trách nhiệm trước pháp luật về tính hợp pháp, trung thực và chính xác của việc ủy quyền. Người ủy quyền và người được ủy quyền phải thực hiện xác thực điện tử để được cấp đăng ký hộ kinh doanh. Trường hợp việc xác thực điện tử bị gián đoạn thì người ủy quyền thực hiện việc xác thực điện tử sau khi được cấp đăng ký hộ kinh doanh. Trường hợp người ủy quyền không xác nhận hoặc xác nhận không ủy quyền thực hiện thủ tục đăng ký hộ kinh doanh thì Cơ quan đăng ký kinh doanh cấp xã yêu cầu hộ kinh doanh báo cáo theo quy định tại khoản 6 Điều 22 Nghị định này.\nTrường hợp chưa có tài khoản định danh điện tử để thực hiện xác thực điện tử thì hồ sơ đăng ký hộ kinh doanh phải kèm theo bản sao thẻ Căn cước hoặc thẻ Căn cước công dân còn hiệu lực của người ủy quyền."
}
